Makefile
base.cfg
bootstrap.py
buildout-plone-5.0.cfg
setup.py
docs/source/HISTORY.rst
docs/source/README.rst
zopyx/__init__.py
zopyx.plone.hyphenator.egg-info/PKG-INFO
zopyx.plone.hyphenator.egg-info/SOURCES.txt
zopyx.plone.hyphenator.egg-info/dependency_links.txt
zopyx.plone.hyphenator.egg-info/entry_points.txt
zopyx.plone.hyphenator.egg-info/namespace_packages.txt
zopyx.plone.hyphenator.egg-info/not-zip-safe
zopyx.plone.hyphenator.egg-info/requires.txt
zopyx.plone.hyphenator.egg-info/top_level.txt
zopyx/plone/__init__.py
zopyx/plone/hyphenator/__init__.py
zopyx/plone/hyphenator/configure.zcml
zopyx/plone/hyphenator/header.txt
zopyx/plone/hyphenator/i18n.py
zopyx/plone/hyphenator/interfaces.py
zopyx/plone/hyphenator/browser/__init__.py
zopyx/plone/hyphenator/browser/configure.zcml
zopyx/plone/hyphenator/browser/controlpanel.py
zopyx/plone/hyphenator/browser/hyphenator.py
zopyx/plone/hyphenator/browser/resources/5.1.0.zip
zopyx/plone/hyphenator/browser/resources/files.txt
zopyx/plone/hyphenator/browser/resources/js-compiled-min.js
zopyx/plone/hyphenator/browser/resources/local.js
zopyx/plone/hyphenator/browser/resources/mergejs
zopyx/plone/hyphenator/browser/resources/hyphenator/Hyphenator.js
zopyx/plone/hyphenator/browser/resources/hyphenator/Hyphenator_Loader.js
zopyx/plone/hyphenator/browser/resources/hyphenator/LICENSE.txt
zopyx/plone/hyphenator/browser/resources/hyphenator/Loader_Example.html
zopyx/plone/hyphenator/browser/resources/hyphenator/README.md
zopyx/plone/hyphenator/browser/resources/hyphenator/WorkingExample.html
zopyx/plone/hyphenator/browser/resources/hyphenator/bower.json
zopyx/plone/hyphenator/browser/resources/hyphenator/compressor.html
zopyx/plone/hyphenator/browser/resources/hyphenator/favicon.ico
zopyx/plone/hyphenator/browser/resources/hyphenator/index.html
zopyx/plone/hyphenator/browser/resources/hyphenator/mergeAndPack.html
zopyx/plone/hyphenator/browser/resources/hyphenator/modalLangDialog.html
zopyx/plone/hyphenator/browser/resources/hyphenator/reducePatternSet.html
zopyx/plone/hyphenator/browser/resources/hyphenator/patterns/be.js
zopyx/plone/hyphenator/browser/resources/hyphenator/patterns/bn.js
zopyx/plone/hyphenator/browser/resources/hyphenator/patterns/ca.js
zopyx/plone/hyphenator/browser/resources/hyphenator/patterns/cs.js
zopyx/plone/hyphenator/browser/resources/hyphenator/patterns/da.js
