Metadata-Version: 1.1
Name: zopyx.plone.hyphenator
Version: 0.1.2
Summary: Hyphenation support for Plone
Home-page: http://pypi.python.org/pypi/zopyx.plone.hyphenator
Author: Andreas Jung
Author-email: info@zopyx.com
License: GPL
Keywords: Plone Hyphenation
Platform: UNKNOWN
Classifier: Programming Language :: Python
Classifier: Framework :: Plone
Classifier: Framework :: Plone :: 5.0
Classifier: Framework :: Zope2
Classifier: Topic :: Software Development :: Libraries :: Python Modules
